{
    "id": "de.dakosy.enhanced-emojis",
    "name": "Enhanced Emojis",
    "version": "0.3.0",
    "description": "Enhances the display of custom emojis in Mattermost.",
    "homepage_url": "https://github.com/marcgoertzen/enhanced-emojis",
    "support_url": "https://github.com/marcgoertzen/enhanced-emojis/issues",
    "icon_path": "assets/enhanced_emojis_icon.png",

    "min_server_version": "10.0.0",
    "settings_schema": {
        "header": "",
        "footer": "",
        "settings": [
            {
                "key": "EnableEnhancedEmojis",
                "display_name": "Enable Enhanced Emojis",
                "type": "bool",
                "help_text": "Controls larger custom emojis in Mattermost post content.",
                "placeholder": "",
                "default": true
            },
            {
                "key": "EnableReactionEmojis",
                "display_name": "Enable Reaction Emojis",
                "type": "bool",
                "help_text": "Controls Enhanced Emojis sizing for custom emoji reactions.",
                "placeholder": "",
                "default": false
            },
            {
                "key": "EnableDeveloperMode",
                "display_name": "Enable Developer Mode",
                "type": "bool",
                "help_text": "Enables visual debugging features for Enhanced Emojis.",
                "placeholder": "",
                "default": false
            }
        ]
    },
    "server": {
        "executable": "server/dist/enhanced-emojis-windows-amd64.exe",
        "executables": {
            "linux-amd64": "server/dist/enhanced-emojis-linux-amd64",
            "darwin-amd64": "server/dist/enhanced-emojis-darwin-amd64",
            "windows-amd64": "server/dist/enhanced-emojis-windows-amd64.exe"
        }
    },

    "webapp": {
        "bundle_path": "webapp/dist/main.js"
    }
}
